eklasescraper/__init__.py
eklasescraper/classes.py
eklasescraper/eklase.py
eklasescraper-0.2.0.dist-info/LICENSE
eklasescraper-0.2.0.dist-info/METADATA
eklasescraper-0.2.0.dist-info/WHEEL
eklasescraper-0.2.0.dist-info/top_level.txt
eklasescraper-0.2.0.dist-info/RECORD
